setup.py
flask_ses/__init__.py
ses_mail.egg-info/PKG-INFO
ses_mail.egg-info/SOURCES.txt
ses_mail.egg-info/dependency_links.txt
ses_mail.egg-info/not-zip-safe
ses_mail.egg-info/requires.txt
ses_mail.egg-info/top_level.txt